odoo10_addon_event_project-10.0.1.0.1-py2.7-nspkg.pth
odoo/addons/event_project/README.rst
odoo/addons/event_project/__init__.py
odoo/addons/event_project/__manifest__.py
odoo/addons/event_project/i18n/es.po
odoo/addons/event_project/i18n/sl.po
odoo/addons/event_project/models/__init__.py
odoo/addons/event_project/models/event_event.py
odoo/addons/event_project/models/project_project.py
odoo/addons/event_project/models/project_task.py
odoo/addons/event_project/security/ir.model.access.csv
odoo/addons/event_project/static/description/icon.png
odoo/addons/event_project/tests/__init__.py
odoo/addons/event_project/tests/test_event_project.py
odoo/addons/event_project/views/event_event_view.xml
odoo/addons/event_project/views/project_project_view.xml
odoo/addons/event_project/views/project_task_view.xml
odoo10_addon_event_project-10.0.1.0.1.dist-info/DESCRIPTION.rst
odoo10_addon_event_project-10.0.1.0.1.dist-info/METADATA
odoo10_addon_event_project-10.0.1.0.1.dist-info/RECORD
odoo10_addon_event_project-10.0.1.0.1.dist-info/WHEEL
odoo10_addon_event_project-10.0.1.0.1.dist-info/metadata.json
odoo10_addon_event_project-10.0.1.0.1.dist-info/namespace_packages.txt
odoo10_addon_event_project-10.0.1.0.1.dist-info/top_level.txt
